{
  "appTitle": "تطبيقي",
  "language": "لغة التطبيق",
  "confirm": "تأكيد",
  "arabic": "اللغة العربية",
  "english": "الإنجليزية",
  "login": "تسجيل الدخول",
  "logout": "تسجيل الخروج",
  "register": "إنشاء حساب",
  "email": "البريد الإلكتروني",
  "password": "كلمة المرور",
  "forgotPassword": "نسيت كلمة المرور؟",
  "welcome": "مرحباً بك",
  "home": "الرئيسية",
  "profile": "الملف الشخصي",
  "settings": "الإعدادات",
  "save": "حفظ",
  "cancel": "إلغاء",
  "submit": "إرسال",
  "edit": "تعديل",
  "delete": "حذف",
  "name": "الاسم",
  "phone": "رقم الجوال",
  "search": "بحث",
  "notifications": "الإشعارات",
  "noData": "لا توجد بيانات حالياً",
  "loading": "جارٍ التحميل...",
  "success": "تم بنجاح",
  "error": "حدث خطأ"
}

